gpcrmining/__init__.py
GPCR_mining-0.1.0.dist-info/LICENSE
GPCR_mining-0.1.0.dist-info/METADATA
GPCR_mining-0.1.0.dist-info/WHEEL
GPCR_mining-0.1.0.dist-info/top_level.txt
GPCR_mining-0.1.0.dist-info/RECORD
